FineTune_Information_Extractor_for_NLPTasks_based_T5_Small/__init__.py
FineTune_Information_Extractor_for_NLPTasks_based_T5_Small/info_extraction.py
FineTune_Information_Extractor_for_NLPTasks_based_T5_Small-1.0.6.dist-info/LICENSE
FineTune_Information_Extractor_for_NLPTasks_based_T5_Small-1.0.6.dist-info/METADATA
FineTune_Information_Extractor_for_NLPTasks_based_T5_Small-1.0.6.dist-info/WHEEL
FineTune_Information_Extractor_for_NLPTasks_based_T5_Small-1.0.6.dist-info/top_level.txt
FineTune_Information_Extractor_for_NLPTasks_based_T5_Small-1.0.6.dist-info/RECORD
